timem.py
timem-0.0.1.dist-info/LICENSE
timem-0.0.1.dist-info/METADATA
timem-0.0.1.dist-info/WHEEL
timem-0.0.1.dist-info/top_level.txt
timem-0.0.1.dist-info/RECORD
