Metadata-Version: 2.1
Name: timem
Version: 0.0.1
Summary: A module for monitoring memory usage of a python program
Home-page: https://github.com/tanaykarve/timem
Author: Tanay Karve
License: BSD
Platform: UNKNOWN
Classifier: Development Status :: 5 - Production/Stable
Classifier: Intended Audience :: Science/Research
Classifier: Intended Audience :: Developers
Classifier: License :: OSI Approved :: MIT License
Classifier: Programming Language :: Python
Classifier: Programming Language :: Python :: 3
Classifier: Topic :: Software Development
Classifier: Operating System :: POSIX
Classifier: Operating System :: Unix
Requires-Python: >=3.4
Requires-Dist: psutil
